check_m_v/missing_values.py
Missing_Values_Check-0.0.1.dist-info/METADATA
Missing_Values_Check-0.0.1.dist-info/WHEEL
Missing_Values_Check-0.0.1.dist-info/top_level.txt
Missing_Values_Check-0.0.1.dist-info/RECORD
