Metadata-Version: 2.1
Name: Missing-Values-Check
Version: 0.0.1
Summary: Check and visualize missing values
Home-page: 
Download-URL: 
Author: jonghokim
Author-email: qkdhfh8@naver.com
License: UNKNOWN
Platform: UNKNOWN
Classifier: Programming Language :: Python :: 3
Classifier: Operating System :: OS Independent
